pipx/__init__.py
pipx/__main__.py
pipx/animate.py
pipx/colors.py
pipx/constants.py
pipx/emojis.py
pipx/interpreter.py
pipx/main.py
pipx/package_specifier.py
pipx/paths.py
pipx/pipx_metadata_file.py
pipx/shared_libs.py
pipx/standalone_python.py
pipx/util.py
pipx/venv.py
pipx/venv_inspect.py
pipx/version.py
pipx/version.pyi
pipx/commands/__init__.py
pipx/commands/common.py
pipx/commands/ensure_path.py
pipx/commands/environment.py
pipx/commands/inject.py
pipx/commands/install.py
pipx/commands/interpreter.py
pipx/commands/list_packages.py
pipx/commands/pin.py
pipx/commands/reinstall.py
pipx/commands/run.py
pipx/commands/run_pip.py
pipx/commands/uninject.py
pipx/commands/uninstall.py
pipx/commands/upgrade.py
pipx-1.7.0.dist-info/METADATA
pipx-1.7.0.dist-info/WHEEL
pipx-1.7.0.dist-info/entry_points.txt
pipx-1.7.0.dist-info/licenses/LICENSE
pipx-1.7.0.dist-info/RECORD
