Metadata-Version: 2.3
Name: pipx
Version: 1.7.0
Summary: Install and Run Python Applications in Isolated Environments
Project-URL: Bug Tracker, https://github.com/pypa/pipx/issues
Project-URL: Documentation, https://pipx.pypa.io
Project-URL: Homepage, https://pipx.pypa.io
Project-URL: Release Notes, https://pipx.pypa.io/latest/changelog/
Project-URL: Source Code, https://github.com/pypa/pipx
Author-email: Chad Smith <chadsmith.software@gmail.com>
License-Expression: MIT
License-File: LICENSE
Keywords: Virtual Environment,cli,install,pip,workflow
Classifier: License :: OSI Approved :: MIT License
Classifier: Operating System :: OS Independent
Classifier: Programming Language :: Python
Classifier: Programming Language :: Python :: 3 :: Only
Classifier: Programming Language :: Python :: 3.8
Classifier: Programming Language :: Python :: 3.9
Classifier: Programming Language :: Python :: 3.10
Classifier: Programming Language :: Python :: 3.11
Classifier: Programming Language :: Python :: 3.12
Requires-Python: >=3.8
Requires-Dist: argcomplete>=1.9.4
Requires-Dist: colorama>=0.4.4; sys_platform == 'win32'
Requires-Dist: packaging>=20
Requires-Dist: platformdirs>=2.1
Requires-Dist: tomli; python_version < '3.11'
Requires-Dist: userpath!=1.9,>=1.6
